{
  "generated_at": "2026-04-01T15:56:05-04:00",
  "news": [
    {
      "headline": "2025-26 NBA championship and MVP odds: Lakers, Wemby making late-season push",
      "description": "The Lakers continue to see their championship odds shorten, while Victor Wembanyama is still in the mix with Shai Gilgeous-Alexander for MVP.",
      "published": "2026-04-01T17:29:25Z",
      "link": "https://www.espn.com/espn/betting/story/_/id/45539787/2025-nba-finals-odds-mvp-2025-26-championship-betting",
      "image_url": "https://a.espncdn.com/photo/2026/0401/r1637203_1296x729_16-9.jpg",
      "source": "ESPN"
    },
    {
      "headline": "NBA Power Rankings: What to watch over the final two weeks for all 30 teams",
      "description": "With just a handful of matchups left for each team in the regular season, where do all 30 teams land in this week's Power Rankings?",
      "published": "2026-04-01T16:24:59Z",
      "link": "https://www.espn.com/nba/story/_/id/48356634/nba-power-rankings-watch-final-two-weeks-all-30-teams",
      "image_url": "https://a.espncdn.com/photo/2026/0331/nba_power_rankings_week22-16x9_608x342.jpg",
      "source": "ESPN"
    },
    {
      "headline": "Next for LeBron? NBA insiders on Lakers, Cavs, free agency options",
      "description": "Lakers? Cavs? Warriors? A wild card? Before LeBron makes his decision this summer, sources around the league weigh in.",
      "published": "2026-03-31T17:33:23Z",
      "link": "https://www.espn.com/nba/story/_/id/48323320/next-lebron-nba-insiders-lakers-warriors-cavs-free-agency-options",
      "image_url": "https://a.espncdn.com/photo/2026/0330/r1636192_1296x729_16-9.jpg",
      "source": "ESPN"
    },
    {
      "headline": "Brown and the Celtics take on conference foe Miami",
      "description": "Boston Celtics (50-25, second in the Eastern Conference) vs. Miami Heat (40-36, ninth in the Eastern Conference)",
      "published": "2026-03-31T06:04:19Z",
      "link": "http://www.espn.com/nba/preview?gameId=401810961",
      "image_url": "https://s.espncdn.com/stitcher/sports/basketball/nba/events/401810961.png?templateId=espn.applewatch.awayhome.1",
      "source": "ESPN"
    },
    {
      "headline": "Philadelphia 76ers vs. Miami Heat: Game Highlights",
      "description": "Philadelphia 76ers vs. Miami Heat: Game Highlights",
      "published": "2026-03-31T02:01:34Z",
      "link": "https://www.espn.com/video/clip?id=48352162",
      "image_url": "https://a.espncdn.com/media/motion/wsc/2026/0331/2d18912c-424f-4db6-80db-6ede33ba21c1/2d18912c-424f-4db6-80db-6ede33ba21c1.jpg",
      "source": "ESPN"
    },
    {
      "headline": "Heat rally late, use 14-0 run in final moments to pull away and beat 76ers 119-109",
      "description": "\u2014 Tyler Herro scored 30 points, Bam Adebayo finished with 23 points and 16 rebounds, and the Miami Heat used a 14-0 run in the final moments to rally past the Philadelphia 76ers 119-109 on Monday night.",
      "published": "2026-03-31T01:56:06Z",
      "link": "http://www.espn.com/nba/recap?gameId=401810946",
      "image_url": "https://s.espncdn.com/stitcher/sports/basketball/nba/events/401810946.png?templateId=espn.applewatch.awayhome.1",
      "source": "ESPN"
    },
    {
      "headline": "Miami plays Philadelphia on home slide",
      "description": "Philadelphia 76ers (41-33, seventh in the Eastern Conference) vs. Miami Heat (39-36, ninth in the Eastern Conference)",
      "published": "2026-03-30T06:04:12Z",
      "link": "http://www.espn.com/nba/preview?gameId=401810946",
      "image_url": "https://s.espncdn.com/stitcher/sports/basketball/nba/events/401810946.png?templateId=espn.applewatch.awayhome.1",
      "source": "ESPN"
    },
    {
      "headline": "Pascal Siakam scores 30 points to give Pacers 135-118 victory that adds to Heat's struggles",
      "description": "\u2014 Pascal Siakam scored 30 points and Micah Potter added 21 and tied a career high with five 3-pointers to help the Indiana Pacers get past the Miami Heat for a rare...",
      "published": "2026-03-30T00:16:02Z",
      "link": "http://www.espn.com/nba/recap?gameId=401810938",
      "image_url": "https://s.espncdn.com/stitcher/sports/basketball/nba/events/401810938.png?templateId=espn.applewatch.awayhome.1",
      "source": "ESPN"
    },
    {
      "headline": "Miami Heat vs. Indiana Pacers: Game Highlights",
      "description": "Miami Heat vs. Indiana Pacers: Game Highlights",
      "published": "2026-03-29T23:47:42Z",
      "link": "https://www.espn.com/video/clip?id=48342810",
      "image_url": "https://a.espncdn.com/media/motion/wsc/2026/0329/26ec90e3-7dcf-49bc-9701-79c91d9e71d5/26ec90e3-7dcf-49bc-9701-79c91d9e71d5.jpg",
      "source": "ESPN"
    },
    {
      "headline": "Indiana plays Miami, looks to break home skid",
      "description": "Miami Heat (39-35, 10th in the Eastern Conference) vs. Indiana Pacers (16-58, 15th in the Eastern Conference)",
      "published": "2026-03-28T06:04:01Z",
      "link": "http://www.espn.com/nba/preview?gameId=401810938",
      "image_url": "https://s.espncdn.com/stitcher/sports/basketball/nba/events/401810938.png?templateId=espn.applewatch.awayhome.1",
      "source": "ESPN"
    },
    {
      "headline": "Max Strus makes eight 3s scores 29, Jarrett Allen returns as Cavs roll to 149-128 win over Heat",
      "description": "\u2014 Max Strus scored 29 points, Evan Mobley had 23 and Jarrett Allen came back from injury to add 18, leading the Cleveland Cavaliers to a 149-128 win over...",
      "published": "2026-03-28T02:25:04Z",
      "link": "http://www.espn.com/nba/recap?gameId=401810923",
      "image_url": "https://s.espncdn.com/stitcher/sports/basketball/nba/events/401810923.png?templateId=espn.applewatch.awayhome.1",
      "source": "ESPN"
    },
    {
      "headline": "Miami Heat vs. Cleveland Cavaliers: Game Highlights",
      "description": "Miami Heat vs. Cleveland Cavaliers: Game Highlights",
      "published": "2026-03-28T02:33:39Z",
      "link": "https://www.espn.com/video/clip?id=48326421",
      "image_url": "https://a.espncdn.com/media/motion/wsc/2026/0328/275e5bf8-7633-4344-938b-450022f58e5a/275e5bf8-7633-4344-938b-450022f58e5a.jpg",
      "source": "ESPN"
    },
    {
      "headline": "Cleveland takes on conference rival Miami",
      "description": "Miami Heat (39-34, eighth in the Eastern Conference) vs. Cleveland Cavaliers (45-28, fourth in the Eastern Conference)",
      "published": "2026-03-26T06:03:18Z",
      "link": "http://www.espn.com/nba/preview?gameId=401810923",
      "image_url": "https://s.espncdn.com/stitcher/sports/basketball/nba/events/401810923.png?templateId=espn.applewatch.awayhome.1",
      "source": "ESPN"
    },
    {
      "headline": "Norman Powell scores 18, Heat use balanced attack to down Cavs 120-103 and snap 5-game skid",
      "description": "\u2014 Norman Powell scored 19 points, Tyler Herro added 18 and the Miami Heat got contributions from everyone while stopping a five-game losing skid with a 120-103 win over the Cleveland Cavaliers on Wednesday night.",
      "published": "2026-03-26T02:49:04Z",
      "link": "http://www.espn.com/nba/recap?gameId=401810910",
      "image_url": "https://s.espncdn.com/stitcher/sports/basketball/nba/events/401810910.png?templateId=espn.applewatch.awayhome.1",
      "source": "ESPN"
    },
    {
      "headline": "Miami Heat vs. Cleveland Cavaliers: Game Highlights",
      "description": "Miami Heat vs. Cleveland Cavaliers: Game Highlights",
      "published": "2026-03-26T02:19:40Z",
      "link": "https://www.espn.com/video/clip?id=48308443",
      "image_url": "https://a.espncdn.com/media/motion/wsc/2026/0326/5b15a10d-e4b0-46ff-9452-4ef7271642d1/5b15a10d-e4b0-46ff-9452-4ef7271642d1.jpg",
      "source": "ESPN"
    }
  ],
  "beat_writers": [
    {
      "name": "Anthony Chiang",
      "handle": "@Anthony_Chiang",
      "outlet": "Miami Herald",
      "role": "Beat Writer",
      "x_url": "https://x.com/Anthony_Chiang"
    },
    {
      "name": "Ira Winderman",
      "handle": "@IraHeatBeat",
      "outlet": "Sun Sentinel",
      "role": "Beat Writer",
      "x_url": "https://x.com/IraHeatBeat"
    },
    {
      "name": "Barry Jackson",
      "handle": "@flasportsbuzz",
      "outlet": "Miami Herald",
      "role": "Columnist",
      "x_url": "https://x.com/flasportsbuzz"
    },
    {
      "name": "Brady Hawk",
      "handle": "@BradyHawk305",
      "outlet": "Five Reasons Sports / OnSI",
      "role": "Writer/Analyst",
      "x_url": "https://x.com/BradyHawk305"
    },
    {
      "name": "Wes Goldberg",
      "handle": "@wcgoldberg",
      "outlet": "Locked On Heat / RealGM",
      "role": "Podcast Host",
      "x_url": "https://x.com/wcgoldberg"
    },
    {
      "name": "Ethan Skolnick",
      "handle": "@EthanJSkolnick",
      "outlet": "Five on the Floor",
      "role": "Podcast Host",
      "x_url": "https://x.com/EthanJSkolnick"
    },
    {
      "name": "David Ramil",
      "handle": "@dramil13",
      "outlet": "Locked On Heat",
      "role": "Podcast Host",
      "x_url": "https://x.com/dramil13"
    },
    {
      "name": "Will Manso",
      "handle": "@WillManso",
      "outlet": "WPLG Local 10",
      "role": "Reporter",
      "x_url": "https://x.com/WillManso"
    },
    {
      "name": "Greg Sylvander",
      "handle": "@GregSylvander",
      "outlet": "Five on the Floor",
      "role": "Co-Host",
      "x_url": "https://x.com/GregSylvander"
    },
    {
      "name": "Couper Moorhead",
      "handle": "@CoupNBA",
      "outlet": "NBA.com / Heat.com",
      "role": "Writer",
      "x_url": "https://x.com/CoupNBA"
    }
  ],
  "featured_tweet_urls": [],
  "data_facts": [
    {
      "category": "record",
      "title": "2-6 Over the Last Two Weeks",
      "body": "Miami has gone 2-6 over the past 14 days, sitting at 40-36 on the season.",
      "stat_value": "2-6",
      "icon": "\u2744\ufe0f"
    },
    {
      "category": "standings",
      "title": "9th Seed in the East",
      "body": "Miami holds the 9th seed (0.526), 15.0 GB of first. Streak: W1.",
      "stat_value": "#9",
      "icon": "\ud83d\udcca"
    },
    {
      "category": "hot_streak",
      "title": "On a 1-Game Winning Streak",
      "body": "The Heat are currently on a 1-game winning streak.",
      "stat_value": "W1",
      "icon": "\ud83d\udd25"
    }
  ],
  "heat_record": {
    "w": 40,
    "l": 36
  },
  "last_14_record": {
    "w": 2,
    "l": 6
  }
}